{
	"dzn_gau": {
		"all": {
			"stage": "mutate",
			"type": "hdsym",
			"cat": "us_equity_index"
		},
		"subsets": {
			"pba": {
				"desc": ["pba_dzn_gau(2)", "pba_dzn_gau(3)", "pba_dzn_gau(4)", "pba_dzn_gau(8)"]
			},
			"vol": {
				"desc": ["vol_dzn_gau(2)", "vol_dzn_gau(3)", "vol_dzn_gau(4)", "vol_dzn_gau(8)"]
			},
			"pba_hdiff1": {
				"desc": ["pba_dzn_hdiff(1)_gau(2)", "pba_dzn_hdiff(1)_gau(3)", "pba_dzn_hdiff(1)_gau(4)", "pba_dzn_hdiff(1)_gau(8)"]
			},
			"vol_hdiff1": {
				"desc": ["vol_dzn_hdiff(1)_gau(2)", "vol_dzn_hdiff(1)_gau(3)", "vol_dzn_hdiff(1)_gau(4)", "vol_dzn_hdiff(1)_gau(8)"]
			}
		}
	},
	"dmx_uni": {
		"all": {
			"stage": "mutate",
			"type": "hdsym",
			"cat": "us_equity_index"
		},
		"subsets": {
			"pba": {
				"desc": ["pba_dmx_uni(2)", "pba_dmx_uni(3)", "pba_dmx_uni(4)", "pba_dmx_uni(8)"]
			},
			"vol": {
				"desc": ["vol_dmx_uni(2)", "vol_dmx_uni(3)", "vol_dmx_uni(4)", "vol_dmx_uni(8)"]
			},
			"pba_hdiff1": {
				"desc": ["pba_dmx_hdiff(1)_uni(2)", "pba_dmx_hdiff(1)_uni(3)", "pba_dmx_hdiff(1)_uni(4)", "pba_dmx_hdiff(1)_uni(8)"]
			},
			"vol_hdiff1": {
				"desc": ["vol_dmx_hdiff(1)_uni(2)", "vol_dmx_hdiff(1)_uni(3)", "vol_dmx_hdiff(1)_uni(4)", "vol_dmx_hdiff(1)_uni(8)"]
			}
		}
	}
}
