{
	"dsma": {
		"all": {
			"stage": "mutate",
			"type": "dsma",
			"cat": "us_equity_index"
		},
		"subsets": {
			"pba": {
				"desc": ["pba_drf_dsma(3)", "pba_drf_dsma(5)", "pba_drf_dsma(10)", "pba_drf_dsma(20)", "pba_drl_dsma(3)", "pba_drl_dsma(5)", "pba_drl_dsma(10)", "pba_drl_dsma(20)"]
			},
			"vol": {
				"desc": ["vol_drf_dsma(3)", "vol_drf_dsma(5)", "vol_drf_dsma(10)", "vol_drf_dsma(20)", "vol_drl_dsma(3)", "vol_drl_dsma(5)", "vol_drl_dsma(10)", "vol_drl_dsma(20)"]
			},
			"trmi_v2": {
				"desc": ["trmi_v2_drf_dsma(3)", "trmi_v2_drf_dsma(5)", "trmi_v2_drf_dsma(10)", "trmi_v2_drf_dsma(20)", "trmi_v2_drl_dsma(3)", "trmi_v2_drl_dsma(5)", "trmi_v2_drl_dsma(10)", "trmi_v2_drl_dsma(20)"]
			},
			"trmi_v3": {
				"desc": ["trmi_v3_drf_dsma(3)", "trmi_v3_drf_dsma(5)", "trmi_v3_drf_dsma(10)", "trmi_v3_drf_dsma(20)", "trmi_v3_drl_dsma(3)", "trmi_v3_drl_dsma(5)", "trmi_v3_drl_dsma(10)", "trmi_v3_drl_dsma(20)"]
			}
		}
	}
}
